__init__.py
bck_euler_angles_rotation.py
bcksmatoolgui.py
calculate_stress.py
calculate_stress_qe.py
elastic_energydensity.py
euler_angles_rotation.py
modify_incar.py
optimize_struct.py
optimize_struct_qe.py
process_stress.py
process_struct.py
read_write.py
shear_tensile_constraint.py
smatoolgui.py
smatoolgui_standalone.py
stress_read_write.py
thermocalc.py
write_inputs.py
smatool-1.1.data/scripts/smatool
smatool-1.1.dist-info/LICENSE
smatool-1.1.dist-info/LICENSE_Main
smatool-1.1.dist-info/METADATA
smatool-1.1.dist-info/WHEEL
smatool-1.1.dist-info/top_level.txt
smatool-1.1.dist-info/RECORD
