Metadata-Version: 2.1
Name: smatool
Version: 1.1
Summary: "SMATool - Automated toolkit for computing zero and finite-temperature strength of materials",
Home-page: https://sourceforge.net/projects/smatool/
Author: Chinedu Ekuma
Author-email: cekuma1@gmail.com
License: GNU GPL version 3
License-File: LICENSE
License-File: LICENSE_Main
Requires-Dist: numpy >=1.20.0
Requires-Dist: scipy >=1.11.0
Requires-Dist: matplotlib >=3.8.0
Requires-Dist: pandas >=1.3.6
Requires-Dist: bottleneck >=1.3.6
Requires-Dist: spglib >=2.1.0
Requires-Dist: pymatgen >=2023.10.11
Requires-Dist: kaleido >=0.2.1
Requires-Dist: plotly >=5.18.0
Requires-Dist: ase >=3.22.1
Requires-Dist: catboost >=1.2.2
Requires-Dist: matminer >=0.9.2
Requires-Dist: scikit-learn >=1.3.2
Requires-Dist: tensorflow >=2.16.1
Requires-Dist: keras >=3.0.5
Requires-Dist: periodictable >=1.7.0
Requires-Dist: pygrace >=1.4
